{
  "updated_at": "06/08 09:37",
  "valid_until": "06/12",
  "max_rate": 31.706,
  "global_emerg": false,
  "data": [
    {
      "name": "台積電",
      "price": "2285",
      "score": 58,
      "sent_icon": "⚪",
      "sent_text": "觀望",
      "signal_label": "牛市(月)",
      "signal_price": "2287",
      "signal_note": "已達標",
      "signal_color": "red",
      "is_crypto": false,
      "emerg": null
    },
    {
      "name": "保德信市值",
      "price": "21",
      "score": 61,
      "sent_icon": "🟢",
      "sent_text": "貪婪",
      "signal_label": "牛市(月)",
      "signal_price": "21",
      "signal_note": "已達標",
      "signal_color": "red",
      "is_crypto": false,
      "emerg": null
    },
    {
      "name": "Solana",
      "price": "65.71",
      "score": 8,
      "sent_icon": "💀",
      "sent_text": "血流成河",
      "signal_label": "熊市(月)",
      "signal_price": "78.80",
      "signal_note": "已達標",
      "signal_color": "red",
      "is_crypto": true,
      "emerg": null
    },
    {
      "name": "Render",
      "price": "1.66",
      "score": 8,
      "sent_icon": "💀",
      "sent_text": "血流成河",
      "signal_label": "熊市(月)",
      "signal_price": "1.95",
      "signal_note": "已達標",
      "signal_color": "red",
      "is_crypto": true,
      "emerg": null
    }
  ]
}