{
  "updated_at": "04/28 10:00",
  "valid_until": "05/01",
  "max_rate": 31.55,
  "global_emerg": false,
  "data": [
    {
      "name": "台積電",
      "price": "2270",
      "score": 84,
      "sent_icon": "🚀",
      "sent_text": "極度貪婪",
      "signal_label": "牛市(中)",
      "signal_price": "1923",
      "signal_note": "(-15.3%)",
      "signal_color": "red",
      "is_crypto": false,
      "emerg": null
    },
    {
      "name": "保德信市值",
      "price": "19",
      "score": 96,
      "sent_icon": "🔥",
      "sent_text": "快逃",
      "signal_label": "牛市(中)",
      "signal_price": "16",
      "signal_note": "(-17.8%)",
      "signal_color": "red",
      "is_crypto": false,
      "emerg": null
    },
    {
      "name": "Solana",
      "price": "84.39",
      "score": 33,
      "sent_icon": "🟠",
      "sent_text": "恐慌",
      "signal_label": "熊市(中)",
      "signal_price": "84.64",
      "signal_note": "已達標",
      "signal_color": "red",
      "is_crypto": true,
      "emerg": null
    },
    {
      "name": "Render",
      "price": "1.78",
      "score": 33,
      "sent_icon": "🟠",
      "sent_text": "恐慌",
      "signal_label": "牛市(中)",
      "signal_price": "1.79",
      "signal_note": "已達標",
      "signal_color": "red",
      "is_crypto": true,
      "emerg": null
    }
  ]
}